AnsibleRumen/README.md
AnsibleRumen/__init__.py
AnsibleRumen/__main__.py
AnsibleRumen/file.epub
AnsibleRumen/index.html
AnsibleRumen/css/__init__.py
AnsibleRumen/css/annotations.css
AnsibleRumen/css/main.css
AnsibleRumen/css/normalize.css
AnsibleRumen/css/popup.css
AnsibleRumen/font/__init__.py
AnsibleRumen/font/fontello.eot
AnsibleRumen/font/fontello.svg
AnsibleRumen/font/fontello.ttf
AnsibleRumen/font/fontello.woff
AnsibleRumen/img/__init__.py
AnsibleRumen/img/annotator-glyph-sprite.png
AnsibleRumen/img/annotator-icon-sprite.png
AnsibleRumen/img/apple-touch-icon.png
AnsibleRumen/img/cancelfullscreen.png
AnsibleRumen/img/close.png
AnsibleRumen/img/fullscreen.png
AnsibleRumen/img/loader.gif
AnsibleRumen/img/menu-icon.png
AnsibleRumen/img/save.png
AnsibleRumen/img/saved.png
AnsibleRumen/img/settings-s.png
AnsibleRumen/img/settings.png
AnsibleRumen/img/star.png
AnsibleRumen/js/__init__.py
AnsibleRumen/js/epub.js
AnsibleRumen/js/epub.min.js
AnsibleRumen/js/epub.min.map
AnsibleRumen/js/hooks.min.js
AnsibleRumen/js/hooks.min.map
AnsibleRumen/js/reader.js
AnsibleRumen/js/reader.js.map
AnsibleRumen/js/reader.min.js
AnsibleRumen/js/reader.min.map
AnsibleRumen/js/hooks/__init__.py
AnsibleRumen/js/hooks/extensions/__init__.py
AnsibleRumen/js/hooks/extensions/highlight.js
AnsibleRumen/js/libs/__init__.py
AnsibleRumen/js/libs/jquery.min.js
AnsibleRumen/js/libs/localforage.min.js
AnsibleRumen/js/libs/screenfull.js
AnsibleRumen/js/libs/screenfull.min.js
AnsibleRumen/js/libs/zip.min.js
AnsibleRumen/js/plugins/__init__.py
AnsibleRumen/js/plugins/hypothesis.js
AnsibleRumen/js/plugins/search.js
ansible_rumen-2024.2.29.0.dist-info/METADATA
ansible_rumen-2024.2.29.0.dist-info/WHEEL
ansible_rumen-2024.2.29.0.dist-info/entry_points.txt
ansible_rumen-2024.2.29.0.dist-info/top_level.txt
ansible_rumen-2024.2.29.0.dist-info/RECORD
